heron_ssl/__init__.py
heron_ssl/augmentations/__init__.py
heron_ssl/augmentations/pipelines.py
heron_ssl/losses/__init__.py
heron_ssl/losses/nt_xent.py
heron_ssl/models/__init__.py
heron_ssl/models/backbones.py
heron_ssl/models/heads.py
heron_ssl/py.typed
heron_ssl/strategies/__init__.py
heron_ssl/strategies/simclr.py
heron_ssl/trainer.py
heron_ssl-0.1.0a1.dist-info/LICENSE
heron_ssl-0.1.0a1.dist-info/METADATA
heron_ssl-0.1.0a1.dist-info/WHEEL
heron_ssl-0.1.0a1.dist-info/RECORD
