Metadata-Version: 2.3
Name: heron-ssl
Version: 0.1.0a1
Summary: A high-level self-supervised learning library on top of JAX
License: MIT
Keywords: self-supervised-learning,pytorch,deep-learning,ssl
Author: Hassan Abedi
Author-email: hassan.abedi.t+heron@gmail.com
Maintainer: Hassan Abedi
Maintainer-email: hassan.abedi.t+heron@gmail.com
Requires-Python: >=3.10,<4.0
Classifier: Development Status :: 3 - Alpha
Classifier: Intended Audience :: Developers
Classifier: License :: OSI Approved :: MIT License
Classifier: Programming Language :: Python :: 3
Classifier: Programming Language :: Python :: 3.10
Classifier: Programming Language :: Python :: 3.11
Classifier: Programming Language :: Python :: 3.12
Classifier: Programming Language :: Python :: 3.13
Classifier: Topic :: Software Development :: Libraries
Classifier: Topic :: Software Development :: Libraries :: Python Modules
Provides-Extra: dev
Requires-Dist: flax (>=0.10.7)
Requires-Dist: griffe (>=1.7.3,<2.0.0) ; extra == "dev"
Requires-Dist: mkdocs (>=1.6.1,<2.0.0) ; extra == "dev"
Requires-Dist: mkdocs-material (>=9.6.14,<10.0.0) ; extra == "dev"
Requires-Dist: mkdocstrings-python (>=1.16.10,<2.0.0) ; extra == "dev"
Requires-Dist: mypy (>=1.11.1) ; extra == "dev"
Requires-Dist: optax (>=0.2.5)
Requires-Dist: pre-commit (>=4.2.0,<5.0.0) ; extra == "dev"
Requires-Dist: pytest (>=8.0.1) ; extra == "dev"
Requires-Dist: pytest-asyncio (>=0.26.0,<0.27.0) ; extra == "dev"
Requires-Dist: pytest-cov (>=6.0.0) ; extra == "dev"
Requires-Dist: pytest-mock (>=3.14.0) ; extra == "dev"
Requires-Dist: ruff (>=0.9.3) ; extra == "dev"
Requires-Dist: types-requests (>=2.32.0.20250515,<3.0.0.0) ; extra == "dev"
Project-URL: Documentation, https://github.com/habedi/heron/blob/main/docs/index.md
Project-URL: Repository, https://github.com/habedi/heron
